odoo/addons/shopinvader_api_invoice/README.rst
odoo/addons/shopinvader_api_invoice/__init__.py
odoo/addons/shopinvader_api_invoice/__manifest__.py
odoo/addons/shopinvader_api_invoice/i18n/shopinvader_api_invoice.pot
odoo/addons/shopinvader_api_invoice/readme/CONTRIBUTORS.rst
odoo/addons/shopinvader_api_invoice/readme/DESCRIPTION.rst
odoo/addons/shopinvader_api_invoice/routers/__init__.py
odoo/addons/shopinvader_api_invoice/routers/invoice.py
odoo/addons/shopinvader_api_invoice/static/description/index.html
odoo/addons/shopinvader_api_invoice/tests/__init__.py
odoo/addons/shopinvader_api_invoice/tests/test_invoice_api.py
odoo_addon_shopinvader_api_invoice-16.0.1.0.1.dist-info/METADATA
odoo_addon_shopinvader_api_invoice-16.0.1.0.1.dist-info/WHEEL
odoo_addon_shopinvader_api_invoice-16.0.1.0.1.dist-info/top_level.txt
odoo_addon_shopinvader_api_invoice-16.0.1.0.1.dist-info/RECORD
